gridgeo/__init__.py
gridgeo/_version.py
gridgeo/cfvariable.py
gridgeo/dask_netcdf.py
gridgeo/gridgeo.py
gridgeo/gridio.py
gridgeo/ugrid.py
gridgeo-1.6.0.dist-info/licenses/LICENSE.txt
gridgeo-1.6.0.dist-info/METADATA
gridgeo-1.6.0.dist-info/WHEEL
gridgeo-1.6.0.dist-info/entry_points.txt
gridgeo-1.6.0.dist-info/top_level.txt
gridgeo-1.6.0.dist-info/zip-safe
gridgeo-1.6.0.dist-info/RECORD
