Metadata-Version: 2.4
Name: gridgeo
Version: 1.6.0
Summary: Convert UGRID, SGRID, and non-compliant ocean model grids to geo-like objects
Author: Filipe Fernandes
Author-email: ocefpaf@gmail.com
License: BSD-3-Clause
Project-URL: homepage, https://github.com/pyoceans/gridgeo
Project-URL: documentation, https://pyoceans.github.io/gridgeo
Project-URL: repository, https://github.com/pyoceans/gridgeo
Platform: any
Requires-Python: >=3.10
License-File: LICENSE.txt
Requires-Dist: docopt
Requires-Dist: netCDF4
Requires-Dist: shapely>=2
Requires-Dist: numpy>=2
Provides-Extra: test
Requires-Dist: cartopy; extra == "test"
Requires-Dist: fiona; extra == "test"
Requires-Dist: folium; extra == "test"
Requires-Dist: hypothesis; extra == "test"
Requires-Dist: matplotlib; extra == "test"
Requires-Dist: nbsphinx; extra == "test"
Requires-Dist: pooch; extra == "test"
Requires-Dist: pytest; extra == "test"
Requires-Dist: pytest-cov; extra == "test"
Requires-Dist: pytest-xdist; extra == "test"
Requires-Dist: sphinx; extra == "test"
Dynamic: license-file
